LICENSE
README.md
setup.cfg
setup.py
bahasa/__init__.py
bahasa.egg-info/PKG-INFO
bahasa.egg-info/SOURCES.txt
bahasa.egg-info/dependency_links.txt
bahasa.egg-info/requires.txt
bahasa.egg-info/top_level.txt
bahasa/data/__init__.py
bahasa/data/kamus.txt
bahasa/stemmer/__init__.py
bahasa/stemmer/context.py
bahasa/stemmer/removal.py
bahasa/stemmer/stemmer.py
bahasa/stemmer/utils.py
bahasa/stemmer/disambiguator/__init__.py
bahasa/stemmer/disambiguator/prefixes/__init__.py
bahasa/stemmer/disambiguator/prefixes/rule_1.py
bahasa/stemmer/disambiguator/prefixes/rule_10.py
bahasa/stemmer/disambiguator/prefixes/rule_11.py
bahasa/stemmer/disambiguator/prefixes/rule_12.py
bahasa/stemmer/disambiguator/prefixes/rule_13.py
bahasa/stemmer/disambiguator/prefixes/rule_14.py
bahasa/stemmer/disambiguator/prefixes/rule_15.py
bahasa/stemmer/disambiguator/prefixes/rule_16.py
bahasa/stemmer/disambiguator/prefixes/rule_17.py
bahasa/stemmer/disambiguator/prefixes/rule_18.py
bahasa/stemmer/disambiguator/prefixes/rule_19.py
bahasa/stemmer/disambiguator/prefixes/rule_2.py
bahasa/stemmer/disambiguator/prefixes/rule_20.py
bahasa/stemmer/disambiguator/prefixes/rule_21.py
bahasa/stemmer/disambiguator/prefixes/rule_23.py
bahasa/stemmer/disambiguator/prefixes/rule_24.py
bahasa/stemmer/disambiguator/prefixes/rule_25.py
bahasa/stemmer/disambiguator/prefixes/rule_26.py
bahasa/stemmer/disambiguator/prefixes/rule_27.py
bahasa/stemmer/disambiguator/prefixes/rule_28.py
bahasa/stemmer/disambiguator/prefixes/rule_29.py
bahasa/stemmer/disambiguator/prefixes/rule_3.py
bahasa/stemmer/disambiguator/prefixes/rule_30.py
bahasa/stemmer/disambiguator/prefixes/rule_31.py
bahasa/stemmer/disambiguator/prefixes/rule_32.py
bahasa/stemmer/disambiguator/prefixes/rule_34.py
bahasa/stemmer/disambiguator/prefixes/rule_35.py
bahasa/stemmer/disambiguator/prefixes/rule_36.py
bahasa/stemmer/disambiguator/prefixes/rule_37.py
bahasa/stemmer/disambiguator/prefixes/rule_38.py
bahasa/stemmer/disambiguator/prefixes/rule_39.py
bahasa/stemmer/disambiguator/prefixes/rule_4.py
bahasa/stemmer/disambiguator/prefixes/rule_40.py
bahasa/stemmer/disambiguator/prefixes/rule_41.py
