Metadata-Version: 2.1
Name: bahasa
Version: 0.0.5
Summary: Bahasa is natural language toolkit for bahasa indonesia
Home-page: https://github.com/kangfend/bahasa
Author: Sutrisno Efendi
Author-email: kangfend@gmail.com
License: MIT
Keywords: NLP,Bahasa,Indonesia,Stemmer
Platform: UNKNOWN
Classifier: Development Status :: 2 - Pre-Alpha
Classifier: Intended Audience :: Developers
Classifier: Topic :: Scientific/Engineering :: Artificial Intelligence
Classifier: Natural Language :: Indonesian
Classifier: Programming Language :: Python
Classifier: License :: OSI Approved :: MIT License
Classifier: Operating System :: OS Independent
Classifier: Topic :: Software Development :: Libraries :: Python Modules
License-File: LICENSE
